{
  "milestones": [
    { "threshold": 10000000, "title": "累计销毁突破 1000万 ZRTA", "message": "社区销毁热情高涨，销毁分红池持续扩大" },
    { "threshold": 20000000, "title": "累计销毁突破 2000万 ZRTA", "message": "销毁里程碑达成，感谢所有参与者" },
    { "threshold": 30000000, "title": "累计销毁突破 3000万 ZRTA", "message": "社区共识不断增强，ZRTA 通缩加速" },
    { "threshold": 40000000, "title": "累计销毁突破 4000万 ZRTA", "message": "销毁量创新高，持币者收益稳步增长" },
    { "threshold": 50000000, "title": "累计销毁突破 5000万 ZRTA", "message": "halfway to the moon! 销毁过半目标" },
    { "threshold": 60000000, "title": "累计销毁突破 6000万 ZRTA", "message": "里程碑达成！社区力量无可阻挡" },
    { "threshold": 70000000, "title": "累计销毁突破 7000万 ZRTA", "message": "销毁进程持续推进" },
    { "threshold": 80000000, "title": "累计销毁突破 8000万 ZRTA", "message": "社区共识达到新高度" },
    { "threshold": 90000000, "title": "累计销毁突破 9000万 ZRTA", "message": "即将达成销毁目标" },
    { "threshold": 100000000, "title": "累计销毁突破 1亿 ZRTA", "message": "历史性里程碑！感谢每一位贡献者" }
  ],
  "dailyMilestones": [
    { "threshold": 1000000, "title": "今日销毁突破 100万 ZRTA", "message": "单日销毁量创新高" },
    { "threshold": 2000000, "title": "今日销毁突破 200万 ZRTA", "message": "销毁热情空前高涨" },
    { "threshold": 5000000, "title": "今日销毁突破 500万 ZRTA", "message": "单日销毁创纪录" }
  ],
  "manual": [
    {
      "id": "1",
      "date": "2026-04-18",
      "title": "MEYieldVault V2 正式上线",
      "message": "新增 Lens 查询合约，优化 Gas 费用，邀请系统全面开放",
      "isNew": true
    },
    {
      "id": "2",
      "date": "2026-04-15",
      "title": "销毁分红池突破 100万 slisBNB",
      "message": "社区累计销毁量达到里程碑，APY 提升至 24.5%"
    }
  ]
}
